ofunctions.network-1.41-py3.11-nspkg.pth
ofunctions/network/__init__.py
ofunctions.network-1.41.dist-info/LICENSE
ofunctions.network-1.41.dist-info/METADATA
ofunctions.network-1.41.dist-info/WHEEL
ofunctions.network-1.41.dist-info/namespace_packages.txt
ofunctions.network-1.41.dist-info/top_level.txt
ofunctions.network-1.41.dist-info/RECORD
